easy_logger/__init__.py
easy_logger/_version.py
easy_logger/decorate.py
easy_logger/log_config.py
easy_logger/log_format.py
easy_logger/statics.py
easy_logger/utils.py
py_easy_logger-0.0.6.dist-info/LICENSE
py_easy_logger-0.0.6.dist-info/METADATA
py_easy_logger-0.0.6.dist-info/WHEEL
py_easy_logger-0.0.6.dist-info/top_level.txt
py_easy_logger-0.0.6.dist-info/zip-safe
py_easy_logger-0.0.6.dist-info/RECORD
