Metadata-Version: 2.1
Name: py-easy-logger
Version: 0.0.6
Summary: Easy Logger
Author-email: atav928 <dev@tavnets.com>
License: GNU GENERAL PUBLIC LICENSE
Project-URL: homepage, https://github.com/atav928/py-easy-logger
Project-URL: documentation, https://github.com/atav928/py-easy-logger
Project-URL: repository, https://github.com/atav928/py-easy-logger
Classifier: License :: OSI Approved :: MIT License
Classifier: Programming Language :: Python :: Implementation
Classifier: Programming Language :: Python :: 3.8
Classifier: Programming Language :: Python :: 3.9
Classifier: Programming Language :: Python :: 3.10
Requires-Python: <4,>=3.8
License-File: LICENSE
Requires-Dist: dataclasses ==0.6
Requires-Dist: colorlog ==6.7.0
Requires-Dist: colorama ==0.4.6
